libdenavit/MASTAN2.py
libdenavit/__init__.py
libdenavit/analysis_helpers.py
libdenavit/camber.py
libdenavit/column_2d.py
libdenavit/cross_section_2d.py
libdenavit/effective_length_factor.py
libdenavit/goal_seek.py
libdenavit/interaction_diagram_2d.py
libdenavit/joist.py
libdenavit/joist_stability.py
libdenavit/non_sway_column_2d.py
libdenavit/plotting.py
libdenavit/sway_column_2d.py
libdenavit/unit_convert.py
libdenavit/utils.py
libdenavit/OpenSees/__init__.py
libdenavit/OpenSees/fiber_section.py
libdenavit/OpenSees/get_fiber_data.py
libdenavit/OpenSees/plotting.py
libdenavit/OpenSees/results.py
libdenavit/OpenSees/uniaxial_material_analysis.py
libdenavit/connections/__init__.py
libdenavit/connections/bolt.py
libdenavit/design/__init__.py
libdenavit/design/tools.py
libdenavit/section/ACI_phi.py
libdenavit/section/ACI_strain_compatibility.py
libdenavit/section/RC.py
libdenavit/section/__init__.py
libdenavit/section/angle.py
libdenavit/section/ccft.py
libdenavit/section/circle_shape.py
libdenavit/section/double_angle.py
libdenavit/section/encased_composite.py
libdenavit/section/fiber_patches.py
libdenavit/section/fiber_section.py
libdenavit/section/geometric_shape.py
libdenavit/section/obround_shape.py
libdenavit/section/rcft.py
libdenavit/section/rectangle_shape.py
libdenavit/section/reinf.py
libdenavit/section/wide_flange.py
libdenavit/section/database/__init__.py
libdenavit/section/database/aci.py
libdenavit/section/database/aisc.py
libdenavit-0.3.dist-info/licenses/LICENSE
libdenavit-0.3.dist-info/METADATA
libdenavit-0.3.dist-info/WHEEL
libdenavit-0.3.dist-info/top_level.txt
libdenavit-0.3.dist-info/RECORD
