Metadata-Version: 2.4
Name: libdenavit
Version: 0.3
Summary: A Python library for structural engineering research.
Home-page: https://github.com/denavit/libdenavit-py
Author: Mark Denavit
Author-email: mdenavit@utk.edu
License: MIT
Requires-Python: >=3.7
License-File: LICENSE
Requires-Dist: matplotlib
Requires-Dist: numpy
Requires-Dist: openseespy
Requires-Dist: pandas
Requires-Dist: Pint
Requires-Dist: scipy
Requires-Dist: shapely
Dynamic: license-file
